aespa/__init__.py
aespa/hello.py
aespa-0.0.1.dist-info/METADATA
aespa-0.0.1.dist-info/WHEEL
aespa-0.0.1.dist-info/licenses/LICENSE
aespa-0.0.1.dist-info/RECORD
