Metadata-Version: 2.4
Name: aespa
Version: 0.0.1
Summary: aespa
Project-URL: Homepage, https://www.aespa.com/
Author-email: jiquanbai <jiquanbai@gmail.com>
License-File: LICENSE
Classifier: License :: OSI Approved :: MIT License
Classifier: Operating System :: OS Independent
Classifier: Programming Language :: Python :: 3
Requires-Python: >=3.10
